MANIFEST.in
README.txt
setup.cfg
setup.py
plonetheme/__init__.py
plonetheme.peerstheme.egg-info/PKG-INFO
plonetheme.peerstheme.egg-info/SOURCES.txt
plonetheme.peerstheme.egg-info/dependency_links.txt
plonetheme.peerstheme.egg-info/entry_points.txt
plonetheme.peerstheme.egg-info/namespace_packages.txt
plonetheme.peerstheme.egg-info/not-zip-safe
plonetheme.peerstheme.egg-info/paster_plugins.txt
plonetheme.peerstheme.egg-info/requires.txt
plonetheme.peerstheme.egg-info/top_level.txt
plonetheme/peerstheme/.DS_Store
plonetheme/peerstheme/__init__.py
plonetheme/peerstheme/configure.zcml
plonetheme/peerstheme/profiles.zcml
plonetheme/peerstheme/setuphandlers.py
plonetheme/peerstheme/skins.zcml
plonetheme/peerstheme/tests.py
plonetheme/peerstheme/version.txt
plonetheme/peerstheme/browser/.DS_Store
plonetheme/peerstheme/browser/__init__.py
plonetheme/peerstheme/browser/configure.zcml
plonetheme/peerstheme/browser/interfaces.py
plonetheme/peerstheme/browser/viewlet.pt
plonetheme/peerstheme/browser/viewlets.py
plonetheme/peerstheme/browser/images/README.txt
plonetheme/peerstheme/browser/stylesheets/README.txt
plonetheme/peerstheme/browser/stylesheets/main.css
plonetheme/peerstheme/profiles/default/.DS_Store
plonetheme/peerstheme/profiles/default/cssregistry.xml
plonetheme/peerstheme/profiles/default/import_steps.xml
plonetheme/peerstheme/profiles/default/jsregistry.xml
plonetheme/peerstheme/profiles/default/metadata.xml
plonetheme/peerstheme/profiles/default/plonetheme.peerstheme_various.txt
plonetheme/peerstheme/profiles/default/skins.xml
plonetheme/peerstheme/profiles/default/viewlets.xml
plonetheme/peerstheme/skins/.DS_Store
plonetheme/peerstheme/skins/plonetheme_peerstheme_custom_images/CONTENT.txt
plonetheme/peerstheme/skins/plonetheme_peerstheme_custom_images/logo.jpg
plonetheme/peerstheme/skins/plonetheme_peerstheme_custom_templates/.DS_Store
plonetheme/peerstheme/skins/plonetheme_peerstheme_custom_templates/CONTENT.txt
plonetheme/peerstheme/skins/plonetheme_peerstheme_custom_templates/default_error_message.pt
plonetheme/peerstheme/skins/plonetheme_peerstheme_custom_templates/sitemap.pt
plonetheme/peerstheme/skins/plonetheme_peerstheme_styles/.DS_Store
plonetheme/peerstheme/skins/plonetheme_peerstheme_styles/CONTENT.txt
plonetheme/peerstheme/skins/plonetheme_peerstheme_styles/base.css.dtml
plonetheme/peerstheme/skins/plonetheme_peerstheme_styles/base_properties.props
