Metadata-Version: 1.0
Name: plonetheme.peerstheme
Version: 1.0b4dev
Summary: An installable theme for Plone 3.0
Home-page: http://medialog.no
Author: Espen Moe-Nilssen
Author-email: espen@medialog.no
License: GPL
Keywords: web zope plone theme
Platform: UNKNOWN
Classifier: Framework :: Plone
Classifier: Programming Language :: Python
Classifier: Topic :: Software Development :: Libraries :: Python Modules
